hpcp.py
hpcp-9.42.dist-info/METADATA
hpcp-9.42.dist-info/WHEEL
hpcp-9.42.dist-info/entry_points.txt
hpcp-9.42.dist-info/top_level.txt
hpcp-9.42.dist-info/RECORD
