Metadata-Version: 2.4
Name: hpcp
Version: 9.42
Summary: Highly Parallel CoPy / HPC coPy: A simple script optimized for distributed file store / NVMe / SSD storage medias for use in High Performace Computing environments.
Home-page: https://github.com/yufei-pan/hpcp
Author: Yufei Pan
Author-email: pan@zopyr.us
License: GPLv3+
Classifier: Programming Language :: Python :: 3
Classifier: License :: OSI Approved :: GNU General Public License v3 or later (GPLv3+)
Classifier: Operating System :: POSIX :: Linux
Classifier: Operating System :: Microsoft :: Windows
Requires-Python: >=3.6
Requires-Dist: argparse
Requires-Dist: xxhash
Requires-Dist: multiCMD>=1.35
Dynamic: author
Dynamic: author-email
Dynamic: classifier
Dynamic: description
Dynamic: description-content-type
Dynamic: home-page
Dynamic: license
Dynamic: requires-dist
Dynamic: requires-python
Dynamic: summary
